unha/__init__.py
unha/unha.py
unha-0.1.3.dist-info/LICENSE
unha-0.1.3.dist-info/METADATA
unha-0.1.3.dist-info/WHEEL
unha-0.1.3.dist-info/top_level.txt
unha-0.1.3.dist-info/RECORD
