Metadata-Version: 2.1
Name: unha
Version: 0.1.3
Summary: A library to simplify telnet connections to Cisco IOS devices
Home-page: https://github.com/orgito/unha
Author: Renato Orgito
Author-email: orgito@gmail.com
Maintainer: Renato Orgito
Maintainer-email: orgito@gmail.com
License: MIT
Project-URL: Bug Reports, https://github.com/orgito/unha/issues
Project-URL: Source, https://github.com/orgito/unha
Keywords: unha network telnet automation
Platform: UNKNOWN
Classifier: Development Status :: 3 - Alpha
Classifier: License :: OSI Approved :: MIT License
Classifier: Operating System :: OS Independent
Classifier: Programming Language :: Python :: 3.4
Classifier: Programming Language :: Python :: 3.5
Classifier: Programming Language :: Python :: 3.6
Classifier: Programming Language :: Python :: 3.7
Requires-Python: >=3.4
